ambience-library.json
ambience.py
sounds/drone/binaural-low-complex.ogg
sounds/machine-planet/serenity.ogg
sounds/nature/amazon-rainforest.ogg
sounds/town/train.ogg
ambience-1.0.13.dist-info/METADATA
ambience-1.0.13.dist-info/WHEEL
ambience-1.0.13.dist-info/entry_points.txt
ambience-1.0.13.dist-info/licenses/LICENSE
ambience-1.0.13.dist-info/RECORD
