Metadata-Version: 2.1
Name: ambience
Version: 1.0.13
Summary: Ambient soundscape player: plays audio files as background ambience
Project-URL: Homepage, https://github.com/sumpygump/ambient
Project-URL: Bug Tracker, https://github.com/sumpygump/ambient/issues
Author-email: Jansen Price <jansen.price@gmail.com>
License-File: LICENSE
Classifier: License :: OSI Approved :: MIT License
Classifier: Operating System :: OS Independent
Classifier: Programming Language :: Python :: 3
Requires-Python: >=3.7
Requires-Dist: pygame
Requires-Dist: requests
